portone_server_sdk/__init__.py
portone_server_sdk/_portone_error.py
portone_server_sdk/_user_agent.py
portone_server_sdk/errors.py
portone_server_sdk/py.typed
portone_server_sdk/webhook.py
portone_server_sdk/_generated/client.py
portone_server_sdk/_generated/errors.py
portone_server_sdk/_generated/auth/client.py
portone_server_sdk/_generated/auth/login_via_api_secret_body.py
portone_server_sdk/_generated/auth/login_via_api_secret_error.py
portone_server_sdk/_generated/auth/login_via_api_secret_response.py
portone_server_sdk/_generated/auth/refresh_token_body.py
portone_server_sdk/_generated/auth/refresh_token_error.py
portone_server_sdk/_generated/auth/refresh_token_response.py
portone_server_sdk/_generated/auth/errors/login_via_api_secret_error.py
portone_server_sdk/_generated/auth/errors/refresh_token_error.py
portone_server_sdk/_generated/b2b/client.py
portone_server_sdk/_generated/b2b/tax_invoice/attach_b2b_tax_invoice_file_body.py
portone_server_sdk/_generated/b2b/tax_invoice/attach_b2b_tax_invoice_file_error.py
portone_server_sdk/_generated/b2b/tax_invoice/b2b_bulk_tax_invoice.py
portone_server_sdk/_generated/b2b/tax_invoice/b2b_bulk_tax_invoice_not_found_error.py
portone_server_sdk/_generated/b2b/tax_invoice/b2b_bulk_tax_invoice_source_type.py
portone_server_sdk/_generated/b2b/tax_invoice/b2b_bulk_tax_invoice_stat.py
portone_server_sdk/_generated/b2b/tax_invoice/b2b_bulk_tax_invoice_status.py
portone_server_sdk/_generated/b2b/tax_invoice/b2b_cannot_change_tax_type_error.py
portone_server_sdk/_generated/b2b/tax_invoice/b2b_company_state_business_status.py
portone_server_sdk/_generated/b2b/tax_invoice/b2b_document_key_cannot_be_changed_error.py
portone_server_sdk/_generated/b2b/tax_invoice/b2b_file_not_found_error.py
portone_server_sdk/_generated/b2b/tax_invoice/b2b_id_already_exists_error.py
portone_server_sdk/_generated/b2b/tax_invoice/b2b_issuance_type_mismatch_error.py
portone_server_sdk/_generated/b2b/tax_invoice/b2b_modification_not_provided_error.py
portone_server_sdk-0.20.0.dist-info/METADATA
portone_server_sdk-0.20.0.dist-info/WHEEL
portone_server_sdk-0.20.0.dist-info/licenses/LICENSE-APACHE
portone_server_sdk-0.20.0.dist-info/licenses/LICENSE-MIT
portone_server_sdk-0.20.0.dist-info/RECORD
