Metadata-Version: 2.4
Name: portone-server-sdk
Version: 0.20.0
Summary: PortOne Python SDK for server-side usage
Project-URL: Documentation, https://portone-io.github.io/server-sdk/py
Project-URL: Repository, https://github.com/portone-io/server-sdk/tree/main/python
Project-URL: Issues, https://github.com/portone-io/server-sdk/issues
Author-email: portone <tech.support@portone.io>, kiwiyou <kiwiyou@portone.io>
License-File: LICENSE-APACHE
License-File: LICENSE-MIT
Requires-Python: >=3.9
Requires-Dist: httpx>=0.28.1
